Metadata-Version: 2.1
Name: wai.annotations.video
Version: 1.0.1
Summary: Various plugins for managing video with wai.annotations.
Home-page: https://github.com/waikato-ufdl/wai-annotations-video
Author: Peter Reutemann
Author-email: fracpete@waikato.ac.nz
License: Apache License Version 2.0
Platform: UNKNOWN
Classifier: Development Status :: 4 - Beta
Classifier: License :: OSI Approved :: Apache Software License
Classifier: Topic :: Scientific/Engineering :: Mathematics
Classifier: Programming Language :: Python :: 3
License-File: LICENSE
